Workbook

Sheet Dashboard
B1: Order Management
B2: Dashboard — KPIs and summary
B4: SALES
B5: Total Sales (ex VAT) | C5: Sales VAT | D5: Sales (gross) | E5: Received | F5: Outstanding (AR)
B6: =SUM(SalesOrders!$J$5:$J$504) -> 5977 | C6: =SUM(SalesOrders!$K$5:$K$504) -> 1195.4 | D6: =SUM(SalesOrders!$L$5:$L$504) -> 7172.4 | E6: =SUMIFS(Payments!$E$5:$E$504,Payments!$C$5:$C$504,"In") -> 2064.8 | F6: =SUM(SalesOrders!$N$5:$N$504) -> 5107.6
B9: PURCHASES
B10: Total Purchases (ex VAT) | C10: Purchase VAT | D10: Purchases (gross) | E10: Paid | F10: Outstanding (AP)
B11: =SUM(PurchaseOrders!$J$5:$J$504) -> 8850 | C11: =SUM(PurchaseOrders!$K$5:$K$504) -> 1770 | D11: =SUM(PurchaseOrders!$L$5:$L$504) -> 10620 | E11: =SUMIFS(Payments!$E$5:$E$504,Payments!$C$5:$C$504,"Out") -> 6168 | F11: =SUM(PurchaseOrders!$N$5:$N$504) -> 4452
B14: VAT POSITION
B15: VAT owed to HMRC | C15: Open SOs | D15: Open POs | E15: Active customers | F15: Active suppliers
B16: =SUM(SalesOrders!$K$5:$K$504)-SUM(PurchaseOrders!$K$5:$K$504) -> -574.6 | C16: =COUNTIFS(SalesOrders!$N$5:$N$504,">0",SalesOrders!$E$5:$E$504,"<>Cancelled") -> 5 | D16: =COUNTIFS(PurchaseOrders!$N$5:$N$504,">0",PurchaseOrders!$E$5:$E$504,"<>Cancelled") -> 2 | E16: =COUNTIFS(Customers!$I$5:$I$504,"Yes") -> 500 | F16: =COUNTIFS(Suppliers!$I$5:$I$504,"Yes") -> 500
B19: SALES ORDERS BY STATUS
B20: Status | C20: Count | D20: Gross Total
B21: Draft | C21: =COUNTIFS(SalesOrders!$E$5:$E$504,"Draft") -> 496 | D21: =SUMIFS(SalesOrders!$L$5:$L$504,SalesOrders!$E$5:$E$504,"Draft") -> 2880
B22: Confirmed | C22: =COUNTIFS(SalesOrders!$E$5:$E$504,"Confirmed") -> 1 | D22: =SUMIFS(SalesOrders!$L$5:$L$504,SalesOrders!$E$5:$E$504,"Confirmed") -> 756
B23: Shipped | C23: =COUNTIFS(SalesOrders!$E$5:$E$504,"Shipped") -> 1 | D23: =SUMIFS(SalesOrders!$L$5:$L$504,SalesOrders!$E$5:$E$504,"Shipped") -> 768
B24: Invoiced | C24: =COUNTIFS(SalesOrders!$E$5:$E$504,"Invoiced") -> 1 | D24: =SUMIFS(SalesOrders!$L$5:$L$504,SalesOrders!$E$5:$E$504,"Invoiced") -> 1254
B25: Paid | C25: =COUNTIFS(SalesOrders!$E$5:$E$504,"Paid") -> 1 | D25: =SUMIFS(SalesOrders!$L$5:$L$504,SalesOrders!$E$5:$E$504,"Paid") -> 1514.4
B26: Cancelled | C26: =COUNTIFS(SalesOrders!$E$5:$E$504,"Cancelled") -> 0 | D26: =SUMIFS(SalesOrders!$L$5:$L$504,SalesOrders!$E$5:$E$504,"Cancelled") -> 0
B29: PURCHASE ORDERS BY STATUS
B30: Status | C30: Count | D30: Gross Total
B31: Draft | C31: =COUNTIFS(PurchaseOrders!$E$5:$E$504,"Draft") -> 496 | D31: =SUMIFS(PurchaseOrders!$L$5:$L$504,PurchaseOrders!$E$5:$E$504,"Draft") -> 0
B32: Sent | C32: =COUNTIFS(PurchaseOrders!$E$5:$E$504,"Sent") -> 1 | D32: =SUMIFS(PurchaseOrders!$L$5:$L$504,PurchaseOrders!$E$5:$E$504,"Sent") -> 1728
B33: Received | C33: =COUNTIFS(PurchaseOrders!$E$5:$E$504,"Received") -> 1 | D33: =SUMIFS(PurchaseOrders!$L$5:$L$504,PurchaseOrders!$E$5:$E$504,"Received") -> 2724
B34: Invoiced | C34: =COUNTIFS(PurchaseOrders!$E$5:$E$504,"Invoiced") -> 1 | D34: =SUMIFS(PurchaseOrders!$L$5:$L$504,PurchaseOrders!$E$5:$E$504,"Invoiced") -> 1080
B35: Paid | C35: =COUNTIFS(PurchaseOrders!$E$5:$E$504,"Paid") -> 1 | D35: =SUMIFS(PurchaseOrders!$L$5:$L$504,PurchaseOrders!$E$5:$E$504,"Paid") -> 5088
B36: Cancelled | C36: =COUNTIFS(PurchaseOrders!$E$5:$E$504,"Cancelled") -> 0 | D36: =SUMIFS(PurchaseOrders!$L$5:$L$504,PurchaseOrders!$E$5:$E$504,"Cancelled") -> 0

Sheet Customers
A1: Customers
A2: People and companies we sell to
A4: customer_id | B4: name | C4: contact_name | D4: email | E4: phone | F4: billing_address | G4: vat_number | H4: credit_limit | I4: active | J4: created_date
A5: CUST-0001 | B5: Acme Engineering Ltd | C5: Sarah Mitchell | D5: orders@acme-eng.co.uk | E5: 020 7946 0101 | F5: 12 Industrial Way, Slough SL1 4AB | G5: GB123456789 | H5: 10000 | I5: Yes | J5: 45933
A6: CUST-0002 | B6: Bright Retail Co | C6: James Patel | D6: ap@brightretail.com | E6: 0161 496 0823 | F6: Unit 5 Park Trading Est, Manchester M12 4BG | G6: GB987654321 | H6: 5000 | I6: Yes | J6: 45993
A7: CUST-0003 | B7: Harbour & Sons | C7: Emma Harbour | D7: emma@harbourandsons.co.uk | E7: 01273 221 094 | F7: 8 Marina Court, Brighton BN1 2FG | H7: 2500 | I7: Yes | J7: 46053
A8: CUST-0004 | B8: Northpoint Services | C8: Daniel Okafor | D8: accounts@northpoint.co.uk | E8: 0113 245 7712 | F8: Regent House, Leeds LS1 5AS | G8: GB445566778 | H8: 7500 | I8: Yes | J8: 46083
I9: Yes
I10: Yes
I11: Yes
I12: Yes
I13: Yes
I14: Yes
I15: Yes
I16: Yes
I17: Yes
I18: Yes
I19: Yes
I20: Yes
... I504: Yes

Sheet Suppliers
A1: Suppliers
A2: People and companies we buy from
A4: supplier_id | B4: name | C4: contact_name | D4: email | E4: phone | F4: address | G4: vat_number | H4: payment_terms_days | I4: active | J4: created_date
A5: SUPP-0001 | B5: Precision Components Ltd | C5: Robert Chen | D5: sales@precisioncomp.co.uk | E5: 01234 567 890 | F5: Factory 3, Bedford MK42 9JJ | G5: GB111222333 | H5: 30 | I5: Yes | J5: 45913
A6: SUPP-0002 | B6: Global Packaging Supplies | C6: Aisha Khan | D6: orders@globalpack.com | E6: 0121 789 4561 | F6: Packham Industrial Park, Birmingham B12 8AZ | G6: GB222333444 | H6: 45 | I6: Yes | J6: 45963
A7: SUPP-0003 | B7: Eastwood Raw Materials | C7: Michael Grant | D7: sales@eastwoodraw.co.uk | E7: 0191 432 9876 | F7: Dock Road, Newcastle NE1 3DF | G7: GB333444555 | H7: 14 | I7: Yes | J7: 46023
H8: 30 | I8: Yes
H9: 30 | I9: Yes
H10: 30 | I10: Yes
H11: 30 | I11: Yes
H12: 30 | I12: Yes
H13: 30 | I13: Yes
H14: 30 | I14: Yes
H15: 30 | I15: Yes
H16: 30 | I16: Yes
H17: 30 | I17: Yes
H18: 30 | I18: Yes
H19: 30 | I19: Yes
... H504: 30 | I504: Yes

Sheet Products
A1: Products
A2: Shared catalogue of goods and services
A4: product_id | B4: sku | C4: name | D4: description | E4: kind | F4: unit | G4: default_sell_price | H4: default_buy_price | I4: default_vat_code | J4: reorder_level | K4: active
A5: PROD-0001 | B5: WIDGET-A | C5: Standard Widget (Type A) | D5: 10mm steel widget, zinc-plated | E5: Both | F5: ea | G5: 12.5 | H5: 4.8 | I5: STD | J5: 50 | K5: Yes
A6: PROD-0002 | B6: WIDGET-B | C6: Premium Widget (Type B) | D6: 15mm stainless widget, polished | E6: Both | F6: ea | G6: 22 | H6: 9.2 | I6: STD | J6: 30 | K6: Yes
A7: PROD-0003 | B7: BOX-SM | C7: Small Packaging Box | D7: 200x150x100mm cardboard box | E7: Both | F7: ea | G7: 1.2 | H7: 0.45 | I7: STD | J7: 500 | K7: Yes
A8: PROD-0004 | B8: SVC-INSTALL | C8: Installation Service | D8: On-site installation (per hour) | E8: Sellable | F8: hour | G8: 85 | H8: 0 | I8: STD | J8: 0 | K8: Yes
A9: PROD-0005 | B9: RAW-STEEL | C9: Raw Steel Sheet | D9: 1.2mm x 1m x 2m sheet | E9: Purchasable | F9: sheet | G9: 0 | H9: 48 | I9: STD | J9: 20 | K9: Yes
A10: PROD-0006 | B10: CONSUMABLE | C10: Workshop Consumables Pack | D10: Gloves, cleaning fluids, fasteners | E10: Purchasable | F10: pack | G10: 0 | H10: 35 | I10: STD | J10: 5 | K10: Yes
E11: Both | F11: ea | I11: STD | J11: 0 | K11: Yes
E12: Both | F12: ea | I12: STD | J12: 0 | K12: Yes
E13: Both | F13: ea | I13: STD | J13: 0 | K13: Yes
E14: Both | F14: ea | I14: STD | J14: 0 | K14: Yes
E15: Both | F15: ea | I15: STD | J15: 0 | K15: Yes
E16: Both | F16: ea | I16: STD | J16: 0 | K16: Yes
E17: Both | F17: ea | I17: STD | J17: 0 | K17: Yes
E18: Both | F18: ea | I18: STD | J18: 0 | K18: Yes
E19: Both | F19: ea | I19: STD | J19: 0 | K19: Yes
E20: Both | F20: ea | I20: STD | J20: 0 | K20: Yes
E21: Both | F21: ea | I21: STD | J21: 0 | K21: Yes
E22: Both | F22: ea | I22: STD | J22: 0 | K22: Yes
... E504: Both | F504: ea | I504: STD | J504: 0 | K504: Yes

Sheet SalesOrders
A1: SalesOrders
A2: Customer orders — header level
A4: order_id | B4: order_date | C4: customer_id | D4: customer_name | E4: status | F4: required_date | G4: shipped_date | H4: po_reference | I4: notes | J4: subtotal | K4: vat_total | L4: grand_total | M4: amount_paid | N4: balance_due
A5: SO-0001 | B5: 46088 | C5: CUST-0001 | D5: =IFERROR(IF(C5="","",INDEX(Customers!$B$5:$B$504,MATCH(C5,Customers!$A$5:$A$504,0))),"") -> Acme Engineering Ltd | E5: Paid | F5: 46098 | G5: 46095 | H5: ACME-PO-8821 | J5: =IFERROR(SUMIFS(SalesOrderLines!$I$5:$I$504,SalesOrderLines!$B$5:$B$504,A5),"") -> 1262 | K5: =IFERROR(SUMIFS(SalesOrderLines!$J$5:$J$504,SalesOrderLines!$B$5:$B$504,A5),"") -> 252.4 | L5: =IFERROR(J5+K5,"") -> 1514.4 | M5: =IFERROR(SUMIFS(Payments!$E$5:$E$504,Payments!$D$5:$D$504,A5,Payments!$C$5:$C$504,"In"),"") -> 1264.8 | N5: =IFERROR(L5-M5,"") -> 249.6
A6: SO-0002 | B6: 46095 | C6: CUST-0002 | D6: =IFERROR(IF(C6="","",INDEX(Customers!$B$5:$B$504,MATCH(C6,Customers!$A$5:$A$504,0))),"") -> Bright Retail Co | E6: Invoiced | F6: 46105 | G6: 46103 | H6: BR-2026-0418 | I6: Deliver to goods-in | J6: =IFERROR(SUMIFS(SalesOrderLines!$I$5:$I$504,SalesOrderLines!$B$5:$B$504,A6),"") -> 1045 | K6: =IFERROR(SUMIFS(SalesOrderLines!$J$5:$J$504,SalesOrderLines!$B$5:$B$504,A6),"") -> 209 | L6: =IFERROR(J6+K6,"") -> 1254 | M6: =IFERROR(SUMIFS(Payments!$E$5:$E$504,Payments!$D$5:$D$504,A6,Payments!$C$5:$C$504,"In"),"") -> 800 | N6: =IFERROR(L6-M6,"") -> 454
A7: SO-0003 | B7: 46103 | C7: CUST-0003 | D7: =IFERROR(IF(C7="","",INDEX(Customers!$B$5:$B$504,MATCH(C7,Customers!$A$5:$A$504,0))),"") -> Harbour & Sons | E7: Shipped | F7: 46111 | G7: 46110 | I7: Phone order | J7: =IFERROR(SUMIFS(SalesOrderLines!$I$5:$I$504,SalesOrderLines!$B$5:$B$504,A7),"") -> 640 | K7: =IFERROR(SUMIFS(SalesOrderLines!$J$5:$J$504,SalesOrderLines!$B$5:$B$504,A7),"") -> 128 | L7: =IFERROR(J7+K7,"") -> 768 | M7: =IFERROR(SUMIFS(Payments!$E$5:$E$504,Payments!$D$5:$D$504,A7,Payments!$C$5:$C$504,"In"),"") -> 0 | N7: =IFERROR(L7-M7,"") -> 768
A8: SO-0004 | B8: 46110 | C8: CUST-0004 | D8: =IFERROR(IF(C8="","",INDEX(Customers!$B$5:$B$504,MATCH(C8,Customers!$A$5:$A$504,0))),"") -> Northpoint Services | E8: Confirmed | F8: 46120 | H8: NP-2026-0088 | J8: =IFERROR(SUMIFS(SalesOrderLines!$I$5:$I$504,SalesOrderLines!$B$5:$B$504,A8),"") -> 630 | K8: =IFERROR(SUMIFS(SalesOrderLines!$J$5:$J$504,SalesOrderLines!$B$5:$B$504,A8),"") -> 126 | L8: =IFERROR(J8+K8,"") -> 756 | M8: =IFERROR(SUMIFS(Payments!$E$5:$E$504,Payments!$D$5:$D$504,A8,Payments!$C$5:$C$504,"In"),"") -> 0 | N8: =IFERROR(L8-M8,"") -> 756
A9: SO-0005 | B9: 46113 | C9: CUST-0001 | D9: =IFERROR(IF(C9="","",INDEX(Customers!$B$5:$B$504,MATCH(C9,Customers!$A$5:$A$504,0))),"") -> Acme Engineering Ltd | E9: Draft | F9: 46127 | I9: Awaiting confirmation | J9: =IFERROR(SUMIFS(SalesOrderLines!$I$5:$I$504,SalesOrderLines!$B$5:$B$504,A9),"") -> 2400 | K9: =IFERROR(SUMIFS(SalesOrderLines!$J$5:$J$504,SalesOrderLines!$B$5:$B$504,A9),"") -> 480 | L9: =IFERROR(J9+K9,"") -> 2880 | M9: =IFERROR(SUMIFS(Payments!$E$5:$E$504,Payments!$D$5:$D$504,A9,Payments!$C$5:$C$504,"In"),"") -> 0 | N9: =IFERROR(L9-M9,"") -> 2880
D10: =IFERROR(IF(C10="","",INDEX(Customers!$B$5:$B$504,MATCH(C10,Customers!$A$5:$A$504,0))),"") | E10: Draft | J10: =IFERROR(SUMIFS(SalesOrderLines!$I$5:$I$504,SalesOrderLines!$B$5:$B$504,A10),"") -> 0 | K10: =IFERROR(SUMIFS(SalesOrderLines!$J$5:$J$504,SalesOrderLines!$B$5:$B$504,A10),"") -> 0 | L10: =IFERROR(J10+K10,"") -> 0 | M10: =IFERROR(SUMIFS(Payments!$E$5:$E$504,Payments!$D$5:$D$504,A10,Payments!$C$5:$C$504,"In"),"") -> 0 | N10: =IFERROR(L10-M10,"") -> 0
D11: =IFERROR(IF(C11="","",INDEX(Customers!$B$5:$B$504,MATCH(C11,Customers!$A$5:$A$504,0))),"") | E11: Draft | J11: =IFERROR(SUMIFS(SalesOrderLines!$I$5:$I$504,SalesOrderLines!$B$5:$B$504,A11),"") -> 0 | K11: =IFERROR(SUMIFS(SalesOrderLines!$J$5:$J$504,SalesOrderLines!$B$5:$B$504,A11),"") -> 0 | L11: =IFERROR(J11+K11,"") -> 0 | M11: =IFERROR(SUMIFS(Payments!$E$5:$E$504,Payments!$D$5:$D$504,A11,Payments!$C$5:$C$504,"In"),"") -> 0 | N11: =IFERROR(L11-M11,"") -> 0
D12: =IFERROR(IF(C12="","",INDEX(Customers!$B$5:$B$504,MATCH(C12,Customers!$A$5:$A$504,0))),"") | E12: Draft | J12: =IFERROR(SUMIFS(SalesOrderLines!$I$5:$I$504,SalesOrderLines!$B$5:$B$504,A12),"") -> 0 | K12: =IFERROR(SUMIFS(SalesOrderLines!$J$5:$J$504,SalesOrderLines!$B$5:$B$504,A12),"") -> 0 | L12: =IFERROR(J12+K12,"") -> 0 | M12: =IFERROR(SUMIFS(Payments!$E$5:$E$504,Payments!$D$5:$D$504,A12,Payments!$C$5:$C$504,"In"),"") -> 0 | N12: =IFERROR(L12-M12,"") -> 0
D13: =IFERROR(IF(C13="","",INDEX(Customers!$B$5:$B$504,MATCH(C13,Customers!$A$5:$A$504,0))),"") | E13: Draft | J13: =IFERROR(SUMIFS(SalesOrderLines!$I$5:$I$504,SalesOrderLines!$B$5:$B$504,A13),"") -> 0 | K13: =IFERROR(SUMIFS(SalesOrderLines!$J$5:$J$504,SalesOrderLines!$B$5:$B$504,A13),"") -> 0 | L13: =IFERROR(J13+K13,"") -> 0 | M13: =IFERROR(SUMIFS(Payments!$E$5:$E$504,Payments!$D$5:$D$504,A13,Payments!$C$5:$C$504,"In"),"") -> 0 | N13: =IFERROR(L13-M13,"") -> 0
D14: =IFERROR(IF(C14="","",INDEX(Customers!$B$5:$B$504,MATCH(C14,Customers!$A$5:$A$504,0))),"") | E14: Draft | J14: =IFERROR(SUMIFS(SalesOrderLines!$I$5:$I$504,SalesOrderLines!$B$5:$B$504,A14),"") -> 0 | K14: =IFERROR(SUMIFS(SalesOrderLines!$J$5:$J$504,SalesOrderLines!$B$5:$B$504,A14),"") -> 0 | L14: =IFERROR(J14+K14,"") -> 0 | M14: =IFERROR(SUMIFS(Payments!$E$5:$E$504,Payments!$D$5:$D$504,A14,Payments!$C$5:$C$504,"In"),"") -> 0 | N14: =IFERROR(L14-M14,"") -> 0
D15: =IFERROR(IF(C15="","",INDEX(Customers!$B$5:$B$504,MATCH(C15,Customers!$A$5:$A$504,0))),"") | E15: Draft | J15: =IFERROR(SUMIFS(SalesOrderLines!$I$5:$I$504,SalesOrderLines!$B$5:$B$504,A15),"") -> 0 | K15: =IFERROR(SUMIFS(SalesOrderLines!$J$5:$J$504,SalesOrderLines!$B$5:$B$504,A15),"") -> 0 | L15: =IFERROR(J15+K15,"") -> 0 | M15: =IFERROR(SUMIFS(Payments!$E$5:$E$504,Payments!$D$5:$D$504,A15,Payments!$C$5:$C$504,"In"),"") -> 0 | N15: =IFERROR(L15-M15,"") -> 0
D16: =IFERROR(IF(C16="","",INDEX(Customers!$B$5:$B$504,MATCH(C16,Customers!$A$5:$A$504,0))),"") | E16: Draft | J16: =IFERROR(SUMIFS(SalesOrderLines!$I$5:$I$504,SalesOrderLines!$B$5:$B$504,A16),"") -> 0 | K16: =IFERROR(SUMIFS(SalesOrderLines!$J$5:$J$504,SalesOrderLines!$B$5:$B$504,A16),"") -> 0 | L16: =IFERROR(J16+K16,"") -> 0 | M16: =IFERROR(SUMIFS(Payments!$E$5:$E$504,Payments!$D$5:$D$504,A16,Payments!$C$5:$C$504,"In"),"") -> 0 | N16: =IFERROR(L16-M16,"") -> 0
D17: =IFERROR(IF(C17="","",INDEX(Customers!$B$5:$B$504,MATCH(C17,Customers!$A$5:$A$504,0))),"") | E17: Draft | J17: =IFERROR(SUMIFS(SalesOrderLines!$I$5:$I$504,SalesOrderLines!$B$5:$B$504,A17),"") -> 0 | K17: =IFERROR(SUMIFS(SalesOrderLines!$J$5:$J$504,SalesOrderLines!$B$5:$B$504,A17),"") -> 0 | L17: =IFERROR(J17+K17,"") -> 0 | M17: =IFERROR(SUMIFS(Payments!$E$5:$E$504,Payments!$D$5:$D$504,A17,Payments!$C$5:$C$504,"In"),"") -> 0 | N17: =IFERROR(L17-M17,"") -> 0
D18: =IFERROR(IF(C18="","",INDEX(Customers!$B$5:$B$504,MATCH(C18,Customers!$A$5:$A$504,0))),"") | E18: Draft | J18: =IFERROR(SUMIFS(SalesOrderLines!$I$5:$I$504,SalesOrderLines!$B$5:$B$504,A18),"") -> 0 | K18: =IFERROR(SUMIFS(SalesOrderLines!$J$5:$J$504,SalesOrderLines!$B$5:$B$504,A18),"") -> 0 | L18: =IFERROR(J18+K18,"") -> 0 | M18: =IFERROR(SUMIFS(Payments!$E$5:$E$504,Payments!$D$5:$D$504,A18,Payments!$C$5:$C$504,"In"),"") -> 0 | N18: =IFERROR(L18-M18,"") -> 0
D19: =IFERROR(IF(C19="","",INDEX(Customers!$B$5:$B$504,MATCH(C19,Customers!$A$5:$A$504,0))),"") | E19: Draft | J19: =IFERROR(SUMIFS(SalesOrderLines!$I$5:$I$504,SalesOrderLines!$B$5:$B$504,A19),"") -> 0 | K19: =IFERROR(SUMIFS(SalesOrderLines!$J$5:$J$504,SalesOrderLines!$B$5:$B$504,A19),"") -> 0 | L19: =IFERROR(J19+K19,"") -> 0 | M19: =IFERROR(SUMIFS(Payments!$E$5:$E$504,Payments!$D$5:$D$504,A19,Payments!$C$5:$C$504,"In"),"") -> 0 | N19: =IFERROR(L19-M19,"") -> 0
D20: =IFERROR(IF(C20="","",INDEX(Customers!$B$5:$B$504,MATCH(C20,Customers!$A$5:$A$504,0))),"") | E20: Draft | J20: =IFERROR(SUMIFS(SalesOrderLines!$I$5:$I$504,SalesOrderLines!$B$5:$B$504,A20),"") -> 0 | K20: =IFERROR(SUMIFS(SalesOrderLines!$J$5:$J$504,SalesOrderLines!$B$5:$B$504,A20),"") -> 0 | L20: =IFERROR(J20+K20,"") -> 0 | M20: =IFERROR(SUMIFS(Payments!$E$5:$E$504,Payments!$D$5:$D$504,A20,Payments!$C$5:$C$504,"In"),"") -> 0 | N20: =IFERROR(L20-M20,"") -> 0
D21: =IFERROR(IF(C21="","",INDEX(Customers!$B$5:$B$504,MATCH(C21,Customers!$A$5:$A$504,0))),"") | E21: Draft | J21: =IFERROR(SUMIFS(SalesOrderLines!$I$5:$I$504,SalesOrderLines!$B$5:$B$504,A21),"") -> 0 | K21: =IFERROR(SUMIFS(SalesOrderLines!$J$5:$J$504,SalesOrderLines!$B$5:$B$504,A21),"") -> 0 | L21: =IFERROR(J21+K21,"") -> 0 | M21: =IFERROR(SUMIFS(Payments!$E$5:$E$504,Payments!$D$5:$D$504,A21,Payments!$C$5:$C$504,"In"),"") -> 0 | N21: =IFERROR(L21-M21,"") -> 0
... D504: =IFERROR(IF(C504="","",INDEX(Customers!$B$5:$B$504,MATCH(C504,Customers!$A$5:$A$504,0))),"") | E504: Draft | J504: =IFERROR(SUMIFS(SalesOrderLines!$I$5:$I$504,SalesOrderLines!$B$5:$B$504,A504),"") -> 0 | K504: =IFERROR(SUMIFS(SalesOrderLines!$J$5:$J$504,SalesOrderLines!$B$5:$B$504,A504),"") -> 0 | L504: =IFERROR(J504+K504,"") -> 0 | M504: =IFERROR(SUMIFS(Payments!$E$5:$E$504,Payments!$D$5:$D$504,A504,Payments!$C$5:$C$504,"In"),"") -> 0 | N504: =IFERROR(L504-M504,"") -> 0

Sheet SalesOrderLines
A1: SalesOrderLines
A2: Line items on sales orders
A4: line_id | B4: order_id | C4: product_id | D4: product_name | E4: quantity | F4: unit_price | G4: discount_pct | H4: vat_code | I4: line_net | J4: line_vat | K4: line_gross
A5: SOL-0001 | B5: SO-0001 | C5: PROD-0001 | D5: =IFERROR(IF(C5="","",INDEX(Products!$C$5:$C$504,MATCH(C5,Products!$A$5:$A$504,0))),"") -> Standard Widget (Type A) | E5: 100 | F5: 12.5 | G5: 0 | H5: STD | I5: =IFERROR(E5*F5*(1-G5),"") -> 1250 | J5: =IFERROR(I5*IFERROR(VLOOKUP(H5,VatRates,2,FALSE()),0),"") -> 250 | K5: =IFERROR(I5+J5,"") -> 1500
A6: SOL-0002 | B6: SO-0001 | C6: PROD-0003 | D6: =IFERROR(IF(C6="","",INDEX(Products!$C$5:$C$504,MATCH(C6,Products!$A$5:$A$504,0))),"") -> Small Packaging Box | E6: 10 | F6: 1.2 | G6: 0 | H6: STD | I6: =IFERROR(E6*F6*(1-G6),"") -> 12 | J6: =IFERROR(I6*IFERROR(VLOOKUP(H6,VatRates,2,FALSE()),0),"") -> 2.4 | K6: =IFERROR(I6+J6,"") -> 14.4
A7: SOL-0003 | B7: SO-0002 | C7: PROD-0002 | D7: =IFERROR(IF(C7="","",INDEX(Products!$C$5:$C$504,MATCH(C7,Products!$A$5:$A$504,0))),"") -> Premium Widget (Type B) | E7: 50 | F7: 22 | G7: 0.05 | H7: STD | I7: =IFERROR(E7*F7*(1-G7),"") -> 1045 | J7: =IFERROR(I7*IFERROR(VLOOKUP(H7,VatRates,2,FALSE()),0),"") -> 209 | K7: =IFERROR(I7+J7,"") -> 1254
A8: SOL-0004 | B8: SO-0003 | C8: PROD-0001 | D8: =IFERROR(IF(C8="","",INDEX(Products!$C$5:$C$504,MATCH(C8,Products!$A$5:$A$504,0))),"") -> Standard Widget (Type A) | E8: 24 | F8: 12.5 | G8: 0 | H8: STD | I8: =IFERROR(E8*F8*(1-G8),"") -> 300 | J8: =IFERROR(I8*IFERROR(VLOOKUP(H8,VatRates,2,FALSE()),0),"") -> 60 | K8: =IFERROR(I8+J8,"") -> 360
A9: SOL-0005 | B9: SO-0003 | C9: PROD-0004 | D9: =IFERROR(IF(C9="","",INDEX(Products!$C$5:$C$504,MATCH(C9,Products!$A$5:$A$504,0))),"") -> Installation Service | E9: 4 | F9: 85 | G9: 0 | H9: STD | I9: =IFERROR(E9*F9*(1-G9),"") -> 340 | J9: =IFERROR(I9*IFERROR(VLOOKUP(H9,VatRates,2,FALSE()),0),"") -> 68 | K9: =IFERROR(I9+J9,"") -> 408
A10: SOL-0006 | B10: SO-0004 | C10: PROD-0002 | D10: =IFERROR(IF(C10="","",INDEX(Products!$C$5:$C$504,MATCH(C10,Products!$A$5:$A$504,0))),"") -> Premium Widget (Type B) | E10: 30 | F10: 22 | G10: 0.1 | H10: STD | I10: =IFERROR(E10*F10*(1-G10),"") -> 594 | J10: =IFERROR(I10*IFERROR(VLOOKUP(H10,VatRates,2,FALSE()),0),"") -> 118.8 | K10: =IFERROR(I10+J10,"") -> 712.8
A11: SOL-0007 | B11: SO-0004 | C11: PROD-0003 | D11: =IFERROR(IF(C11="","",INDEX(Products!$C$5:$C$504,MATCH(C11,Products!$A$5:$A$504,0))),"") -> Small Packaging Box | E11: 30 | F11: 1.2 | G11: 0 | H11: STD | I11: =IFERROR(E11*F11*(1-G11),"") -> 36 | J11: =IFERROR(I11*IFERROR(VLOOKUP(H11,VatRates,2,FALSE()),0),"") -> 7.2 | K11: =IFERROR(I11+J11,"") -> 43.2
A12: SOL-0008 | B12: SO-0005 | C12: PROD-0001 | D12: =IFERROR(IF(C12="","",INDEX(Products!$C$5:$C$504,MATCH(C12,Products!$A$5:$A$504,0))),"") -> Standard Widget (Type A) | E12: 200 | F12: 12 | G12: 0 | H12: STD | I12: =IFERROR(E12*F12*(1-G12),"") -> 2400 | J12: =IFERROR(I12*IFERROR(VLOOKUP(H12,VatRates,2,FALSE()),0),"") -> 480 | K12: =IFERROR(I12+J12,"") -> 2880
D13: =IFERROR(IF(C13="","",INDEX(Products!$C$5:$C$504,MATCH(C13,Products!$A$5:$A$504,0))),"") | E13: 1 | G13: 0 | H13: STD | I13: =IFERROR(E13*F13*(1-G13),"") -> 0 | J13: =IFERROR(I13*IFERROR(VLOOKUP(H13,VatRates,2,FALSE()),0),"") -> 0 | K13: =IFERROR(I13+J13,"") -> 0
D14: =IFERROR(IF(C14="","",INDEX(Products!$C$5:$C$504,MATCH(C14,Products!$A$5:$A$504,0))),"") | E14: 1 | G14: 0 | H14: STD | I14: =IFERROR(E14*F14*(1-G14),"") -> 0 | J14: =IFERROR(I14*IFERROR(VLOOKUP(H14,VatRates,2,FALSE()),0),"") -> 0 | K14: =IFERROR(I14+J14,"") -> 0
D15: =IFERROR(IF(C15="","",INDEX(Products!$C$5:$C$504,MATCH(C15,Products!$A$5:$A$504,0))),"") | E15: 1 | G15: 0 | H15: STD | I15: =IFERROR(E15*F15*(1-G15),"") -> 0 | J15: =IFERROR(I15*IFERROR(VLOOKUP(H15,VatRates,2,FALSE()),0),"") -> 0 | K15: =IFERROR(I15+J15,"") -> 0
D16: =IFERROR(IF(C16="","",INDEX(Products!$C$5:$C$504,MATCH(C16,Products!$A$5:$A$504,0))),"") | E16: 1 | G16: 0 | H16: STD | I16: =IFERROR(E16*F16*(1-G16),"") -> 0 | J16: =IFERROR(I16*IFERROR(VLOOKUP(H16,VatRates,2,FALSE()),0),"") -> 0 | K16: =IFERROR(I16+J16,"") -> 0
D17: =IFERROR(IF(C17="","",INDEX(Products!$C$5:$C$504,MATCH(C17,Products!$A$5:$A$504,0))),"") | E17: 1 | G17: 0 | H17: STD | I17: =IFERROR(E17*F17*(1-G17),"") -> 0 | J17: =IFERROR(I17*IFERROR(VLOOKUP(H17,VatRates,2,FALSE()),0),"") -> 0 | K17: =IFERROR(I17+J17,"") -> 0
D18: =IFERROR(IF(C18="","",INDEX(Products!$C$5:$C$504,MATCH(C18,Products!$A$5:$A$504,0))),"") | E18: 1 | G18: 0 | H18: STD | I18: =IFERROR(E18*F18*(1-G18),"") -> 0 | J18: =IFERROR(I18*IFERROR(VLOOKUP(H18,VatRates,2,FALSE()),0),"") -> 0 | K18: =IFERROR(I18+J18,"") -> 0
D19: =IFERROR(IF(C19="","",INDEX(Products!$C$5:$C$504,MATCH(C19,Products!$A$5:$A$504,0))),"") | E19: 1 | G19: 0 | H19: STD | I19: =IFERROR(E19*F19*(1-G19),"") -> 0 | J19: =IFERROR(I19*IFERROR(VLOOKUP(H19,VatRates,2,FALSE()),0),"") -> 0 | K19: =IFERROR(I19+J19,"") -> 0
D20: =IFERROR(IF(C20="","",INDEX(Products!$C$5:$C$504,MATCH(C20,Products!$A$5:$A$504,0))),"") | E20: 1 | G20: 0 | H20: STD | I20: =IFERROR(E20*F20*(1-G20),"") -> 0 | J20: =IFERROR(I20*IFERROR(VLOOKUP(H20,VatRates,2,FALSE()),0),"") -> 0 | K20: =IFERROR(I20+J20,"") -> 0
D21: =IFERROR(IF(C21="","",INDEX(Products!$C$5:$C$504,MATCH(C21,Products!$A$5:$A$504,0))),"") | E21: 1 | G21: 0 | H21: STD | I21: =IFERROR(E21*F21*(1-G21),"") -> 0 | J21: =IFERROR(I21*IFERROR(VLOOKUP(H21,VatRates,2,FALSE()),0),"") -> 0 | K21: =IFERROR(I21+J21,"") -> 0
D22: =IFERROR(IF(C22="","",INDEX(Products!$C$5:$C$504,MATCH(C22,Products!$A$5:$A$504,0))),"") | E22: 1 | G22: 0 | H22: STD | I22: =IFERROR(E22*F22*(1-G22),"") -> 0 | J22: =IFERROR(I22*IFERROR(VLOOKUP(H22,VatRates,2,FALSE()),0),"") -> 0 | K22: =IFERROR(I22+J22,"") -> 0
D23: =IFERROR(IF(C23="","",INDEX(Products!$C$5:$C$504,MATCH(C23,Products!$A$5:$A$504,0))),"") | E23: 1 | G23: 0 | H23: STD | I23: =IFERROR(E23*F23*(1-G23),"") -> 0 | J23: =IFERROR(I23*IFERROR(VLOOKUP(H23,VatRates,2,FALSE()),0),"") -> 0 | K23: =IFERROR(I23+J23,"") -> 0
D24: =IFERROR(IF(C24="","",INDEX(Products!$C$5:$C$504,MATCH(C24,Products!$A$5:$A$504,0))),"") | E24: 1 | G24: 0 | H24: STD | I24: =IFERROR(E24*F24*(1-G24),"") -> 0 | J24: =IFERROR(I24*IFERROR(VLOOKUP(H24,VatRates,2,FALSE()),0),"") -> 0 | K24: =IFERROR(I24+J24,"") -> 0
... D504: =IFERROR(IF(C504="","",INDEX(Products!$C$5:$C$504,MATCH(C504,Products!$A$5:$A$504,0))),"") | E504: 1 | G504: 0 | H504: STD | I504: =IFERROR(E504*F504*(1-G504),"") -> 0 | J504: =IFERROR(I504*IFERROR(VLOOKUP(H504,VatRates,2,FALSE()),0),"") -> 0 | K504: =IFERROR(I504+J504,"") -> 0

Sheet PurchaseOrders
A1: PurchaseOrders
A2: Orders placed with suppliers — header level
A4: po_id | B4: po_date | C4: supplier_id | D4: supplier_name | E4: status | F4: expected_date | G4: received_date | H4: supplier_invoice_ref | I4: notes | J4: subtotal | K4: vat_total | L4: grand_total | M4: amount_paid | N4: balance_due
A5: PO-0001 | B5: 46053 | C5: SUPP-0001 | D5: =IFERROR(IF(C5="","",INDEX(Suppliers!$B$5:$B$504,MATCH(C5,Suppliers!$A$5:$A$504,0))),"") -> Precision Components Ltd | E5: Paid | F5: 46068 | G5: 46066 | H5: PC-INV-44221 | J5: =IFERROR(SUMIFS(PurchaseOrderLines!$H$5:$H$504,PurchaseOrderLines!$B$5:$B$504,A5),"") -> 4240 | K5: =IFERROR(SUMIFS(PurchaseOrderLines!$I$5:$I$504,PurchaseOrderLines!$B$5:$B$504,A5),"") -> 848 | L5: =IFERROR(J5+K5,"") -> 5088 | M5: =IFERROR(SUMIFS(Payments!$E$5:$E$504,Payments!$D$5:$D$504,A5,Payments!$C$5:$C$504,"Out"),"") -> 5088 | N5: =IFERROR(L5-M5,"") -> 0
A6: PO-0002 | B6: 46078 | C6: SUPP-0002 | D6: =IFERROR(IF(C6="","",INDEX(Suppliers!$B$5:$B$504,MATCH(C6,Suppliers!$A$5:$A$504,0))),"") -> Global Packaging Supplies | E6: Invoiced | F6: 46093 | G6: 46091 | H6: GP-0119-26 | J6: =IFERROR(SUMIFS(PurchaseOrderLines!$H$5:$H$504,PurchaseOrderLines!$B$5:$B$504,A6),"") -> 900 | K6: =IFERROR(SUMIFS(PurchaseOrderLines!$I$5:$I$504,PurchaseOrderLines!$B$5:$B$504,A6),"") -> 180 | L6: =IFERROR(J6+K6,"") -> 1080 | M6: =IFERROR(SUMIFS(Payments!$E$5:$E$504,Payments!$D$5:$D$504,A6,Payments!$C$5:$C$504,"Out"),"") -> 1080 | N6: =IFERROR(L6-M6,"") -> 0
A7: PO-0003 | B7: 46101 | C7: SUPP-0003 | D7: =IFERROR(IF(C7="","",INDEX(Suppliers!$B$5:$B$504,MATCH(C7,Suppliers!$A$5:$A$504,0))),"") -> Eastwood Raw Materials | E7: Received | F7: 46108 | G7: 46109 | I7: Invoice awaited | J7: =IFERROR(SUMIFS(PurchaseOrderLines!$H$5:$H$504,PurchaseOrderLines!$B$5:$B$504,A7),"") -> 2270 | K7: =IFERROR(SUMIFS(PurchaseOrderLines!$I$5:$I$504,PurchaseOrderLines!$B$5:$B$504,A7),"") -> 454 | L7: =IFERROR(J7+K7,"") -> 2724 | M7: =IFERROR(SUMIFS(Payments!$E$5:$E$504,Payments!$D$5:$D$504,A7,Payments!$C$5:$C$504,"Out"),"") -> 0 | N7: =IFERROR(L7-M7,"") -> 2724
A8: PO-0004 | B8: 46111 | C8: SUPP-0001 | D8: =IFERROR(IF(C8="","",INDEX(Suppliers!$B$5:$B$504,MATCH(C8,Suppliers!$A$5:$A$504,0))),"") -> Precision Components Ltd | E8: Sent | F8: 46125 | J8: =IFERROR(SUMIFS(PurchaseOrderLines!$H$5:$H$504,PurchaseOrderLines!$B$5:$B$504,A8),"") -> 1440 | K8: =IFERROR(SUMIFS(PurchaseOrderLines!$I$5:$I$504,PurchaseOrderLines!$B$5:$B$504,A8),"") -> 288 | L8: =IFERROR(J8+K8,"") -> 1728 | M8: =IFERROR(SUMIFS(Payments!$E$5:$E$504,Payments!$D$5:$D$504,A8,Payments!$C$5:$C$504,"Out"),"") -> 0 | N8: =IFERROR(L8-M8,"") -> 1728
D9: =IFERROR(IF(C9="","",INDEX(Suppliers!$B$5:$B$504,MATCH(C9,Suppliers!$A$5:$A$504,0))),"") | E9: Draft | J9: =IFERROR(SUMIFS(PurchaseOrderLines!$H$5:$H$504,PurchaseOrderLines!$B$5:$B$504,A9),"") -> 0 | K9: =IFERROR(SUMIFS(PurchaseOrderLines!$I$5:$I$504,PurchaseOrderLines!$B$5:$B$504,A9),"") -> 0 | L9: =IFERROR(J9+K9,"") -> 0 | M9: =IFERROR(SUMIFS(Payments!$E$5:$E$504,Payments!$D$5:$D$504,A9,Payments!$C$5:$C$504,"Out"),"") -> 0 | N9: =IFERROR(L9-M9,"") -> 0
D10: =IFERROR(IF(C10="","",INDEX(Suppliers!$B$5:$B$504,MATCH(C10,Suppliers!$A$5:$A$504,0))),"") | E10: Draft | J10: =IFERROR(SUMIFS(PurchaseOrderLines!$H$5:$H$504,PurchaseOrderLines!$B$5:$B$504,A10),"") -> 0 | K10: =IFERROR(SUMIFS(PurchaseOrderLines!$I$5:$I$504,PurchaseOrderLines!$B$5:$B$504,A10),"") -> 0 | L10: =IFERROR(J10+K10,"") -> 0 | M10: =IFERROR(SUMIFS(Payments!$E$5:$E$504,Payments!$D$5:$D$504,A10,Payments!$C$5:$C$504,"Out"),"") -> 0 | N10: =IFERROR(L10-M10,"") -> 0
D11: =IFERROR(IF(C11="","",INDEX(Suppliers!$B$5:$B$504,MATCH(C11,Suppliers!$A$5:$A$504,0))),"") | E11: Draft | J11: =IFERROR(SUMIFS(PurchaseOrderLines!$H$5:$H$504,PurchaseOrderLines!$B$5:$B$504,A11),"") -> 0 | K11: =IFERROR(SUMIFS(PurchaseOrderLines!$I$5:$I$504,PurchaseOrderLines!$B$5:$B$504,A11),"") -> 0 | L11: =IFERROR(J11+K11,"") -> 0 | M11: =IFERROR(SUMIFS(Payments!$E$5:$E$504,Payments!$D$5:$D$504,A11,Payments!$C$5:$C$504,"Out"),"") -> 0 | N11: =IFERROR(L11-M11,"") -> 0
D12: =IFERROR(IF(C12="","",INDEX(Suppliers!$B$5:$B$504,MATCH(C12,Suppliers!$A$5:$A$504,0))),"") | E12: Draft | J12: =IFERROR(SUMIFS(PurchaseOrderLines!$H$5:$H$504,PurchaseOrderLines!$B$5:$B$504,A12),"") -> 0 | K12: =IFERROR(SUMIFS(PurchaseOrderLines!$I$5:$I$504,PurchaseOrderLines!$B$5:$B$504,A12),"") -> 0 | L12: =IFERROR(J12+K12,"") -> 0 | M12: =IFERROR(SUMIFS(Payments!$E$5:$E$504,Payments!$D$5:$D$504,A12,Payments!$C$5:$C$504,"Out"),"") -> 0 | N12: =IFERROR(L12-M12,"") -> 0
D13: =IFERROR(IF(C13="","",INDEX(Suppliers!$B$5:$B$504,MATCH(C13,Suppliers!$A$5:$A$504,0))),"") | E13: Draft | J13: =IFERROR(SUMIFS(PurchaseOrderLines!$H$5:$H$504,PurchaseOrderLines!$B$5:$B$504,A13),"") -> 0 | K13: =IFERROR(SUMIFS(PurchaseOrderLines!$I$5:$I$504,PurchaseOrderLines!$B$5:$B$504,A13),"") -> 0 | L13: =IFERROR(J13+K13,"") -> 0 | M13: =IFERROR(SUMIFS(Payments!$E$5:$E$504,Payments!$D$5:$D$504,A13,Payments!$C$5:$C$504,"Out"),"") -> 0 | N13: =IFERROR(L13-M13,"") -> 0
D14: =IFERROR(IF(C14="","",INDEX(Suppliers!$B$5:$B$504,MATCH(C14,Suppliers!$A$5:$A$504,0))),"") | E14: Draft | J14: =IFERROR(SUMIFS(PurchaseOrderLines!$H$5:$H$504,PurchaseOrderLines!$B$5:$B$504,A14),"") -> 0 | K14: =IFERROR(SUMIFS(PurchaseOrderLines!$I$5:$I$504,PurchaseOrderLines!$B$5:$B$504,A14),"") -> 0 | L14: =IFERROR(J14+K14,"") -> 0 | M14: =IFERROR(SUMIFS(Payments!$E$5:$E$504,Payments!$D$5:$D$504,A14,Payments!$C$5:$C$504,"Out"),"") -> 0 | N14: =IFERROR(L14-M14,"") -> 0
D15: =IFERROR(IF(C15="","",INDEX(Suppliers!$B$5:$B$504,MATCH(C15,Suppliers!$A$5:$A$504,0))),"") | E15: Draft | J15: =IFERROR(SUMIFS(PurchaseOrderLines!$H$5:$H$504,PurchaseOrderLines!$B$5:$B$504,A15),"") -> 0 | K15: =IFERROR(SUMIFS(PurchaseOrderLines!$I$5:$I$504,PurchaseOrderLines!$B$5:$B$504,A15),"") -> 0 | L15: =IFERROR(J15+K15,"") -> 0 | M15: =IFERROR(SUMIFS(Payments!$E$5:$E$504,Payments!$D$5:$D$504,A15,Payments!$C$5:$C$504,"Out"),"") -> 0 | N15: =IFERROR(L15-M15,"") -> 0
D16: =IFERROR(IF(C16="","",INDEX(Suppliers!$B$5:$B$504,MATCH(C16,Suppliers!$A$5:$A$504,0))),"") | E16: Draft | J16: =IFERROR(SUMIFS(PurchaseOrderLines!$H$5:$H$504,PurchaseOrderLines!$B$5:$B$504,A16),"") -> 0 | K16: =IFERROR(SUMIFS(PurchaseOrderLines!$I$5:$I$504,PurchaseOrderLines!$B$5:$B$504,A16),"") -> 0 | L16: =IFERROR(J16+K16,"") -> 0 | M16: =IFERROR(SUMIFS(Payments!$E$5:$E$504,Payments!$D$5:$D$504,A16,Payments!$C$5:$C$504,"Out"),"") -> 0 | N16: =IFERROR(L16-M16,"") -> 0
D17: =IFERROR(IF(C17="","",INDEX(Suppliers!$B$5:$B$504,MATCH(C17,Suppliers!$A$5:$A$504,0))),"") | E17: Draft | J17: =IFERROR(SUMIFS(PurchaseOrderLines!$H$5:$H$504,PurchaseOrderLines!$B$5:$B$504,A17),"") -> 0 | K17: =IFERROR(SUMIFS(PurchaseOrderLines!$I$5:$I$504,PurchaseOrderLines!$B$5:$B$504,A17),"") -> 0 | L17: =IFERROR(J17+K17,"") -> 0 | M17: =IFERROR(SUMIFS(Payments!$E$5:$E$504,Payments!$D$5:$D$504,A17,Payments!$C$5:$C$504,"Out"),"") -> 0 | N17: =IFERROR(L17-M17,"") -> 0
D18: =IFERROR(IF(C18="","",INDEX(Suppliers!$B$5:$B$504,MATCH(C18,Suppliers!$A$5:$A$504,0))),"") | E18: Draft | J18: =IFERROR(SUMIFS(PurchaseOrderLines!$H$5:$H$504,PurchaseOrderLines!$B$5:$B$504,A18),"") -> 0 | K18: =IFERROR(SUMIFS(PurchaseOrderLines!$I$5:$I$504,PurchaseOrderLines!$B$5:$B$504,A18),"") -> 0 | L18: =IFERROR(J18+K18,"") -> 0 | M18: =IFERROR(SUMIFS(Payments!$E$5:$E$504,Payments!$D$5:$D$504,A18,Payments!$C$5:$C$504,"Out"),"") -> 0 | N18: =IFERROR(L18-M18,"") -> 0
D19: =IFERROR(IF(C19="","",INDEX(Suppliers!$B$5:$B$504,MATCH(C19,Suppliers!$A$5:$A$504,0))),"") | E19: Draft | J19: =IFERROR(SUMIFS(PurchaseOrderLines!$H$5:$H$504,PurchaseOrderLines!$B$5:$B$504,A19),"") -> 0 | K19: =IFERROR(SUMIFS(PurchaseOrderLines!$I$5:$I$504,PurchaseOrderLines!$B$5:$B$504,A19),"") -> 0 | L19: =IFERROR(J19+K19,"") -> 0 | M19: =IFERROR(SUMIFS(Payments!$E$5:$E$504,Payments!$D$5:$D$504,A19,Payments!$C$5:$C$504,"Out"),"") -> 0 | N19: =IFERROR(L19-M19,"") -> 0
D20: =IFERROR(IF(C20="","",INDEX(Suppliers!$B$5:$B$504,MATCH(C20,Suppliers!$A$5:$A$504,0))),"") | E20: Draft | J20: =IFERROR(SUMIFS(PurchaseOrderLines!$H$5:$H$504,PurchaseOrderLines!$B$5:$B$504,A20),"") -> 0 | K20: =IFERROR(SUMIFS(PurchaseOrderLines!$I$5:$I$504,PurchaseOrderLines!$B$5:$B$504,A20),"") -> 0 | L20: =IFERROR(J20+K20,"") -> 0 | M20: =IFERROR(SUMIFS(Payments!$E$5:$E$504,Payments!$D$5:$D$504,A20,Payments!$C$5:$C$504,"Out"),"") -> 0 | N20: =IFERROR(L20-M20,"") -> 0
... D504: =IFERROR(IF(C504="","",INDEX(Suppliers!$B$5:$B$504,MATCH(C504,Suppliers!$A$5:$A$504,0))),"") | E504: Draft | J504: =IFERROR(SUMIFS(PurchaseOrderLines!$H$5:$H$504,PurchaseOrderLines!$B$5:$B$504,A504),"") -> 0 | K504: =IFERROR(SUMIFS(PurchaseOrderLines!$I$5:$I$504,PurchaseOrderLines!$B$5:$B$504,A504),"") -> 0 | L504: =IFERROR(J504+K504,"") -> 0 | M504: =IFERROR(SUMIFS(Payments!$E$5:$E$504,Payments!$D$5:$D$504,A504,Payments!$C$5:$C$504,"Out"),"") -> 0 | N504: =IFERROR(L504-M504,"") -> 0

Sheet PurchaseOrderLines
A1: PurchaseOrderLines
A2: Line items on purchase orders
A4: line_id | B4: po_id | C4: product_id | D4: product_name | E4: quantity | F4: unit_price | G4: vat_code | H4: line_net | I4: line_vat | J4: line_gross | K4: quantity_received
A5: POL-0001 | B5: PO-0001 | C5: PROD-0001 | D5: =IFERROR(IF(C5="","",INDEX(Products!$C$5:$C$504,MATCH(C5,Products!$A$5:$A$504,0))),"") -> Standard Widget (Type A) | E5: 500 | F5: 4.8 | G5: STD | H5: =IFERROR(E5*F5,"") -> 2400 | I5: =IFERROR(H5*IFERROR(VLOOKUP(G5,VatRates,2,FALSE()),0),"") -> 480 | J5: =IFERROR(H5+I5,"") -> 2880 | K5: 500
A6: POL-0002 | B6: PO-0001 | C6: PROD-0002 | D6: =IFERROR(IF(C6="","",INDEX(Products!$C$5:$C$504,MATCH(C6,Products!$A$5:$A$504,0))),"") -> Premium Widget (Type B) | E6: 200 | F6: 9.2 | G6: STD | H6: =IFERROR(E6*F6,"") -> 1840 | I6: =IFERROR(H6*IFERROR(VLOOKUP(G6,VatRates,2,FALSE()),0),"") -> 368 | J6: =IFERROR(H6+I6,"") -> 2208 | K6: 200
A7: POL-0003 | B7: PO-0002 | C7: PROD-0003 | D7: =IFERROR(IF(C7="","",INDEX(Products!$C$5:$C$504,MATCH(C7,Products!$A$5:$A$504,0))),"") -> Small Packaging Box | E7: 2000 | F7: 0.45 | G7: STD | H7: =IFERROR(E7*F7,"") -> 900 | I7: =IFERROR(H7*IFERROR(VLOOKUP(G7,VatRates,2,FALSE()),0),"") -> 180 | J7: =IFERROR(H7+I7,"") -> 1080 | K7: 2000
A8: POL-0004 | B8: PO-0003 | C8: PROD-0005 | D8: =IFERROR(IF(C8="","",INDEX(Products!$C$5:$C$504,MATCH(C8,Products!$A$5:$A$504,0))),"") -> Raw Steel Sheet | E8: 40 | F8: 48 | G8: STD | H8: =IFERROR(E8*F8,"") -> 1920 | I8: =IFERROR(H8*IFERROR(VLOOKUP(G8,VatRates,2,FALSE()),0),"") -> 384 | J8: =IFERROR(H8+I8,"") -> 2304 | K8: 40
A9: POL-0005 | B9: PO-0003 | C9: PROD-0006 | D9: =IFERROR(IF(C9="","",INDEX(Products!$C$5:$C$504,MATCH(C9,Products!$A$5:$A$504,0))),"") -> Workshop Consumables Pack | E9: 10 | F9: 35 | G9: STD | H9: =IFERROR(E9*F9,"") -> 350 | I9: =IFERROR(H9*IFERROR(VLOOKUP(G9,VatRates,2,FALSE()),0),"") -> 70 | J9: =IFERROR(H9+I9,"") -> 420 | K9: 10
A10: POL-0006 | B10: PO-0004 | C10: PROD-0001 | D10: =IFERROR(IF(C10="","",INDEX(Products!$C$5:$C$504,MATCH(C10,Products!$A$5:$A$504,0))),"") -> Standard Widget (Type A) | E10: 300 | F10: 4.8 | G10: STD | H10: =IFERROR(E10*F10,"") -> 1440 | I10: =IFERROR(H10*IFERROR(VLOOKUP(G10,VatRates,2,FALSE()),0),"") -> 288 | J10: =IFERROR(H10+I10,"") -> 1728 | K10: 0
D11: =IFERROR(IF(C11="","",INDEX(Products!$C$5:$C$504,MATCH(C11,Products!$A$5:$A$504,0))),"") | E11: 1 | G11: STD | H11: =IFERROR(E11*F11,"") -> 0 | I11: =IFERROR(H11*IFERROR(VLOOKUP(G11,VatRates,2,FALSE()),0),"") -> 0 | J11: =IFERROR(H11+I11,"") -> 0 | K11: 0
D12: =IFERROR(IF(C12="","",INDEX(Products!$C$5:$C$504,MATCH(C12,Products!$A$5:$A$504,0))),"") | E12: 1 | G12: STD | H12: =IFERROR(E12*F12,"") -> 0 | I12: =IFERROR(H12*IFERROR(VLOOKUP(G12,VatRates,2,FALSE()),0),"") -> 0 | J12: =IFERROR(H12+I12,"") -> 0 | K12: 0
D13: =IFERROR(IF(C13="","",INDEX(Products!$C$5:$C$504,MATCH(C13,Products!$A$5:$A$504,0))),"") | E13: 1 | G13: STD | H13: =IFERROR(E13*F13,"") -> 0 | I13: =IFERROR(H13*IFERROR(VLOOKUP(G13,VatRates,2,FALSE()),0),"") -> 0 | J13: =IFERROR(H13+I13,"") -> 0 | K13: 0
D14: =IFERROR(IF(C14="","",INDEX(Products!$C$5:$C$504,MATCH(C14,Products!$A$5:$A$504,0))),"") | E14: 1 | G14: STD | H14: =IFERROR(E14*F14,"") -> 0 | I14: =IFERROR(H14*IFERROR(VLOOKUP(G14,VatRates,2,FALSE()),0),"") -> 0 | J14: =IFERROR(H14+I14,"") -> 0 | K14: 0
D15: =IFERROR(IF(C15="","",INDEX(Products!$C$5:$C$504,MATCH(C15,Products!$A$5:$A$504,0))),"") | E15: 1 | G15: STD | H15: =IFERROR(E15*F15,"") -> 0 | I15: =IFERROR(H15*IFERROR(VLOOKUP(G15,VatRates,2,FALSE()),0),"") -> 0 | J15: =IFERROR(H15+I15,"") -> 0 | K15: 0
D16: =IFERROR(IF(C16="","",INDEX(Products!$C$5:$C$504,MATCH(C16,Products!$A$5:$A$504,0))),"") | E16: 1 | G16: STD | H16: =IFERROR(E16*F16,"") -> 0 | I16: =IFERROR(H16*IFERROR(VLOOKUP(G16,VatRates,2,FALSE()),0),"") -> 0 | J16: =IFERROR(H16+I16,"") -> 0 | K16: 0
D17: =IFERROR(IF(C17="","",INDEX(Products!$C$5:$C$504,MATCH(C17,Products!$A$5:$A$504,0))),"") | E17: 1 | G17: STD | H17: =IFERROR(E17*F17,"") -> 0 | I17: =IFERROR(H17*IFERROR(VLOOKUP(G17,VatRates,2,FALSE()),0),"") -> 0 | J17: =IFERROR(H17+I17,"") -> 0 | K17: 0
D18: =IFERROR(IF(C18="","",INDEX(Products!$C$5:$C$504,MATCH(C18,Products!$A$5:$A$504,0))),"") | E18: 1 | G18: STD | H18: =IFERROR(E18*F18,"") -> 0 | I18: =IFERROR(H18*IFERROR(VLOOKUP(G18,VatRates,2,FALSE()),0),"") -> 0 | J18: =IFERROR(H18+I18,"") -> 0 | K18: 0
D19: =IFERROR(IF(C19="","",INDEX(Products!$C$5:$C$504,MATCH(C19,Products!$A$5:$A$504,0))),"") | E19: 1 | G19: STD | H19: =IFERROR(E19*F19,"") -> 0 | I19: =IFERROR(H19*IFERROR(VLOOKUP(G19,VatRates,2,FALSE()),0),"") -> 0 | J19: =IFERROR(H19+I19,"") -> 0 | K19: 0
D20: =IFERROR(IF(C20="","",INDEX(Products!$C$5:$C$504,MATCH(C20,Products!$A$5:$A$504,0))),"") | E20: 1 | G20: STD | H20: =IFERROR(E20*F20,"") -> 0 | I20: =IFERROR(H20*IFERROR(VLOOKUP(G20,VatRates,2,FALSE()),0),"") -> 0 | J20: =IFERROR(H20+I20,"") -> 0 | K20: 0
D21: =IFERROR(IF(C21="","",INDEX(Products!$C$5:$C$504,MATCH(C21,Products!$A$5:$A$504,0))),"") | E21: 1 | G21: STD | H21: =IFERROR(E21*F21,"") -> 0 | I21: =IFERROR(H21*IFERROR(VLOOKUP(G21,VatRates,2,FALSE()),0),"") -> 0 | J21: =IFERROR(H21+I21,"") -> 0 | K21: 0
D22: =IFERROR(IF(C22="","",INDEX(Products!$C$5:$C$504,MATCH(C22,Products!$A$5:$A$504,0))),"") | E22: 1 | G22: STD | H22: =IFERROR(E22*F22,"") -> 0 | I22: =IFERROR(H22*IFERROR(VLOOKUP(G22,VatRates,2,FALSE()),0),"") -> 0 | J22: =IFERROR(H22+I22,"") -> 0 | K22: 0
... D504: =IFERROR(IF(C504="","",INDEX(Products!$C$5:$C$504,MATCH(C504,Products!$A$5:$A$504,0))),"") | E504: 1 | G504: STD | H504: =IFERROR(E504*F504,"") -> 0 | I504: =IFERROR(H504*IFERROR(VLOOKUP(G504,VatRates,2,FALSE()),0),"") -> 0 | J504: =IFERROR(H504+I504,"") -> 0 | K504: 0

Sheet Payments
A1: Payments
A2: Payments received from customers or made to suppliers
A4: payment_id | B4: payment_date | C4: direction | D4: reference_id | E4: amount | F4: method | G4: reference | H4: notes
A5: PAY-0001 | B5: 46098 | C5: In | D5: SO-0001 | E5: 1264.8 | F5: Bank Transfer | G5: ACME-REMIT-0918
A6: PAY-0002 | B6: 46107 | C6: In | D6: SO-0002 | E6: 800 | F6: Bank Transfer | G6: BR-PART-001 | H6: Part payment
A7: PAY-0003 | B7: 46073 | C7: Out | D7: PO-0001 | E7: 5088 | F7: Bank Transfer | G7: BACS-26-0219
A8: PAY-0004 | B8: 46105 | C8: Out | D8: PO-0002 | E8: 1080 | F8: Bank Transfer | G8: BACS-26-0404
F9: Bank Transfer
F10: Bank Transfer
F11: Bank Transfer
F12: Bank Transfer
F13: Bank Transfer
F14: Bank Transfer
F15: Bank Transfer
F16: Bank Transfer
F17: Bank Transfer
F18: Bank Transfer
F19: Bank Transfer
F20: Bank Transfer
... F504: Bank Transfer

Sheet InventoryMovements
A1: InventoryMovements
A2: Stock movements — positive for receipts, negative for dispatches
A4: movement_id | B4: movement_date | C4: product_id | D4: product_name | E4: quantity | F4: movement_type | G4: reference_id | H4: notes
A5: MOV-0001 | B5: 46066 | C5: PROD-0001 | D5: =IFERROR(IF(C5="","",INDEX(Products!$C$5:$C$504,MATCH(C5,Products!$A$5:$A$504,0))),"") -> Standard Widget (Type A) | E5: 500 | F5: Receipt | G5: PO-0001
A6: MOV-0002 | B6: 46066 | C6: PROD-0002 | D6: =IFERROR(IF(C6="","",INDEX(Products!$C$5:$C$504,MATCH(C6,Products!$A$5:$A$504,0))),"") -> Premium Widget (Type B) | E6: 200 | F6: Receipt | G6: PO-0001
A7: MOV-0003 | B7: 46091 | C7: PROD-0003 | D7: =IFERROR(IF(C7="","",INDEX(Products!$C$5:$C$504,MATCH(C7,Products!$A$5:$A$504,0))),"") -> Small Packaging Box | E7: 2000 | F7: Receipt | G7: PO-0002
A8: MOV-0004 | B8: 46109 | C8: PROD-0005 | D8: =IFERROR(IF(C8="","",INDEX(Products!$C$5:$C$504,MATCH(C8,Products!$A$5:$A$504,0))),"") -> Raw Steel Sheet | E8: 40 | F8: Receipt | G8: PO-0003
A9: MOV-0005 | B9: 46109 | C9: PROD-0006 | D9: =IFERROR(IF(C9="","",INDEX(Products!$C$5:$C$504,MATCH(C9,Products!$A$5:$A$504,0))),"") -> Workshop Consumables Pack | E9: 10 | F9: Receipt | G9: PO-0003
A10: MOV-0006 | B10: 46095 | C10: PROD-0001 | D10: =IFERROR(IF(C10="","",INDEX(Products!$C$5:$C$504,MATCH(C10,Products!$A$5:$A$504,0))),"") -> Standard Widget (Type A) | E10: -100 | F10: Dispatch | G10: SO-0001
A11: MOV-0007 | B11: 46095 | C11: PROD-0003 | D11: =IFERROR(IF(C11="","",INDEX(Products!$C$5:$C$504,MATCH(C11,Products!$A$5:$A$504,0))),"") -> Small Packaging Box | E11: -10 | F11: Dispatch | G11: SO-0001
A12: MOV-0008 | B12: 46103 | C12: PROD-0002 | D12: =IFERROR(IF(C12="","",INDEX(Products!$C$5:$C$504,MATCH(C12,Products!$A$5:$A$504,0))),"") -> Premium Widget (Type B) | E12: -50 | F12: Dispatch | G12: SO-0002
A13: MOV-0009 | B13: 46110 | C13: PROD-0001 | D13: =IFERROR(IF(C13="","",INDEX(Products!$C$5:$C$504,MATCH(C13,Products!$A$5:$A$504,0))),"") -> Standard Widget (Type A) | E13: -24 | F13: Dispatch | G13: SO-0003
D14: =IFERROR(IF(C14="","",INDEX(Products!$C$5:$C$504,MATCH(C14,Products!$A$5:$A$504,0))),"")
D15: =IFERROR(IF(C15="","",INDEX(Products!$C$5:$C$504,MATCH(C15,Products!$A$5:$A$504,0))),"")
D16: =IFERROR(IF(C16="","",INDEX(Products!$C$5:$C$504,MATCH(C16,Products!$A$5:$A$504,0))),"")
D17: =IFERROR(IF(C17="","",INDEX(Products!$C$5:$C$504,MATCH(C17,Products!$A$5:$A$504,0))),"")
D18: =IFERROR(IF(C18="","",INDEX(Products!$C$5:$C$504,MATCH(C18,Products!$A$5:$A$504,0))),"")
D19: =IFERROR(IF(C19="","",INDEX(Products!$C$5:$C$504,MATCH(C19,Products!$A$5:$A$504,0))),"")
D20: =IFERROR(IF(C20="","",INDEX(Products!$C$5:$C$504,MATCH(C20,Products!$A$5:$A$504,0))),"")
D21: =IFERROR(IF(C21="","",INDEX(Products!$C$5:$C$504,MATCH(C21,Products!$A$5:$A$504,0))),"")
D22: =IFERROR(IF(C22="","",INDEX(Products!$C$5:$C$504,MATCH(C22,Products!$A$5:$A$504,0))),"")
D23: =IFERROR(IF(C23="","",INDEX(Products!$C$5:$C$504,MATCH(C23,Products!$A$5:$A$504,0))),"")
D24: =IFERROR(IF(C24="","",INDEX(Products!$C$5:$C$504,MATCH(C24,Products!$A$5:$A$504,0))),"")
D25: =IFERROR(IF(C25="","",INDEX(Products!$C$5:$C$504,MATCH(C25,Products!$A$5:$A$504,0))),"")
... D504: =IFERROR(IF(C504="","",INDEX(Products!$C$5:$C$504,MATCH(C504,Products!$A$5:$A$504,0))),"")

Sheet StockLevels
A1: Stock Levels
A2: Current stock position per product (formula-driven)
A4: product_id | B4: name | C4: on_hand | D4: reorder_level | E4: reorder_status
A5: =IF(Products!A5="","",Products!A5) -> PROD-0001 | B5: =IF(Products!A5="","",Products!C5) -> Standard Widget (Type A) | C5: =IF(A5="","",SUMIFS(InventoryMovements!$E$5:$E$504,InventoryMovements!$C$5:$C$504,A5)) -> 376 | D5: =IF(A5="","",Products!J5) -> 50 | E5: =IF(A5="","",IF(C5<=D5,"REORDER","OK")) -> OK
A6: =IF(Products!A6="","",Products!A6) -> PROD-0002 | B6: =IF(Products!A6="","",Products!C6) -> Premium Widget (Type B) | C6: =IF(A6="","",SUMIFS(InventoryMovements!$E$5:$E$504,InventoryMovements!$C$5:$C$504,A6)) -> 150 | D6: =IF(A6="","",Products!J6) -> 30 | E6: =IF(A6="","",IF(C6<=D6,"REORDER","OK")) -> OK
A7: =IF(Products!A7="","",Products!A7) -> PROD-0003 | B7: =IF(Products!A7="","",Products!C7) -> Small Packaging Box | C7: =IF(A7="","",SUMIFS(InventoryMovements!$E$5:$E$504,InventoryMovements!$C$5:$C$504,A7)) -> 1990 | D7: =IF(A7="","",Products!J7) -> 500 | E7: =IF(A7="","",IF(C7<=D7,"REORDER","OK")) -> OK
A8: =IF(Products!A8="","",Products!A8) -> PROD-0004 | B8: =IF(Products!A8="","",Products!C8) -> Installation Service | C8: =IF(A8="","",SUMIFS(InventoryMovements!$E$5:$E$504,InventoryMovements!$C$5:$C$504,A8)) -> 0 | D8: =IF(A8="","",Products!J8) -> 0 | E8: =IF(A8="","",IF(C8<=D8,"REORDER","OK")) -> REORDER
A9: =IF(Products!A9="","",Products!A9) -> PROD-0005 | B9: =IF(Products!A9="","",Products!C9) -> Raw Steel Sheet | C9: =IF(A9="","",SUMIFS(InventoryMovements!$E$5:$E$504,InventoryMovements!$C$5:$C$504,A9)) -> 40 | D9: =IF(A9="","",Products!J9) -> 20 | E9: =IF(A9="","",IF(C9<=D9,"REORDER","OK")) -> OK
A10: =IF(Products!A10="","",Products!A10) -> PROD-0006 | B10: =IF(Products!A10="","",Products!C10) -> Workshop Consumables Pack | C10: =IF(A10="","",SUMIFS(InventoryMovements!$E$5:$E$504,InventoryMovements!$C$5:$C$504,A10)) -> 10 | D10: =IF(A10="","",Products!J10) -> 5 | E10: =IF(A10="","",IF(C10<=D10,"REORDER","OK")) -> OK
A11: =IF(Products!A11="","",Products!A11) | B11: =IF(Products!A11="","",Products!C11) | C11: =IF(A11="","",SUMIFS(InventoryMovements!$E$5:$E$504,InventoryMovements!$C$5:$C$504,A11)) | D11: =IF(A11="","",Products!J11) | E11: =IF(A11="","",IF(C11<=D11,"REORDER","OK"))
A12: =IF(Products!A12="","",Products!A12) | B12: =IF(Products!A12="","",Products!C12) | C12: =IF(A12="","",SUMIFS(InventoryMovements!$E$5:$E$504,InventoryMovements!$C$5:$C$504,A12)) | D12: =IF(A12="","",Products!J12) | E12: =IF(A12="","",IF(C12<=D12,"REORDER","OK"))
A13: =IF(Products!A13="","",Products!A13) | B13: =IF(Products!A13="","",Products!C13) | C13: =IF(A13="","",SUMIFS(InventoryMovements!$E$5:$E$504,InventoryMovements!$C$5:$C$504,A13)) | D13: =IF(A13="","",Products!J13) | E13: =IF(A13="","",IF(C13<=D13,"REORDER","OK"))
A14: =IF(Products!A14="","",Products!A14) | B14: =IF(Products!A14="","",Products!C14) | C14: =IF(A14="","",SUMIFS(InventoryMovements!$E$5:$E$504,InventoryMovements!$C$5:$C$504,A14)) | D14: =IF(A14="","",Products!J14) | E14: =IF(A14="","",IF(C14<=D14,"REORDER","OK"))
A15: =IF(Products!A15="","",Products!A15) | B15: =IF(Products!A15="","",Products!C15) | C15: =IF(A15="","",SUMIFS(InventoryMovements!$E$5:$E$504,InventoryMovements!$C$5:$C$504,A15)) | D15: =IF(A15="","",Products!J15) | E15: =IF(A15="","",IF(C15<=D15,"REORDER","OK"))
A16: =IF(Products!A16="","",Products!A16) | B16: =IF(Products!A16="","",Products!C16) | C16: =IF(A16="","",SUMIFS(InventoryMovements!$E$5:$E$504,InventoryMovements!$C$5:$C$504,A16)) | D16: =IF(A16="","",Products!J16) | E16: =IF(A16="","",IF(C16<=D16,"REORDER","OK"))
... A504: =IF(Products!A504="","",Products!A504) | B504: =IF(Products!A504="","",Products!C504) | C504: =IF(A504="","",SUMIFS(InventoryMovements!$E$5:$E$504,InventoryMovements!$C$5:$C$504,A504)) | D504: =IF(A504="","",Products!J504) | E504: =IF(A504="","",IF(C504<=D504,"REORDER","OK"))

Sheet _VatRates
A1: code | B1: rate
A2: STD | B2: 0.2
A3: RED | B3: 0.05
A4: ZER | B4: 0
A5: EXM | B5: 0
A6: OSC | B6: 0

Sheet _Enums
A1: order_status | B1: po_status | C1: vat_code | D1: product_kind | E1: payment_method | F1: payment_direction
A2: Draft | B2: Draft | C2: STD | D2: Sellable | E2: Bank Transfer | F2: In
A3: Confirmed | B3: Sent | C3: RED | D3: Purchasable | E3: Card | F3: Out
A4: Shipped | B4: Received | C4: ZER | D4: Both | E4: Cash
A5: Invoiced | B5: Invoiced | C5: EXM | E5: Cheque
A6: Paid | B6: Paid | C6: OSC | E6: Other
A7: Cancelled | B7: Cancelled
